Metadata-Version: 2.1
Name: MinecraftWS
Version: 1.1.1
Summary: Minecraft Bedrock Websocket
Home-page: https://github.com/Beta5051/MinecraftWS
Author: beta5051
Author-email: beta5051@gmail.com
License: MIT
Platform: UNKNOWN
